{
  "id": "16ae7856-6f65-4823-9f5b-c54998256d69",
  "created_at": "2026-06-12T17:04:11.067399",
  "mood": "Overthinking",
  "user_context": "i missing my best brother from anthor mother",
  "hook": "Nobody talks about how much brothers love you in silence.",
  "slide2": "I saw his hoodie hanging in my closet today. Still smells like him. And I can't breathe.",
  "slide3": "Why does missing someone feel like a stomach punch but nothing else in your body works right?",
  "slide4": "I keep checking old messages like he might have replied just now. Duh. He won\u2019t.",
  "closer": "What\u2019s one thing you wish you could tell him right now?",
  "caption": "It\u2019s 3am and I\u2019m crying over a hoodie. Missing my brother from another mother feels stupid until it doesn\u2019t. We don\u2019t talk about the quiet ways people love us outside of home. Who else is up at this hour feeling this too? \n\n#MissingYou #BrotherLove #LateNightFeels #AnotherMother",
  "hashtags": [
    "missingyou",
    "brotherlove",
    "latenightfeels",
    "anothermother",
    "siblinglove",
    "3amthoughts",
    "cantfallasleep",
    "indianhome"
  ],
  "design": null,
  "scheduled_for": null,
  "status": "draft"
}